./.gitignore
./.readthedocs.yaml
./LICENSE
./PKG-INFO
./README.md
./mkdocs.yml
./noxfile.py
./pyproject.toml
./bak_dist/pyapix-2025.2.14-py3-none-any.whl
./bak_dist/pyapix-2025.2.14.tar.gz
./bak_dist/pyapix-2025.2.2-py3-none-any.whl
./bak_dist/pyapix-2025.2.2.tar.gz
./bak_dist/pyapix-2025.2.7-py3-none-any.whl
./bak_dist/pyapix-2025.2.7.tar.gz
./docs/defining_clients.md
./docs/design.md
./docs/exp_jsonpath.py.20250310172850
./docs/fetch_code_blocks.py
./docs/index.md
./docs/leverage_postman.md
./docs/peemish.md
./docs/todo.md
./docs/using_it.md
./docs/using_it_bio.md
./docs/using_it_nws.md
./docs/using_it_osdu.md
./docs/using_it_petstore.md
./docs/using_template.md
./prose/design/deltaJ.md
./prose/design/overall.md
./prose/design/pyapix.md
./prose/goal/osdu.md
./prose/rnd/exp_jsonpath.py
./prose/rnd/json_overlays.md
./prose/rnd/json_path.md
./prose/task/deployment.md
./prose/task/jdiff.md
./prose/task/postman.md
./prose/task/template.md
./pyapix/__init__.py
./pyapix/client/info.py
./pyapix/client/nws.py
./pyapix/client/obis.py
./pyapix/client/petstore.py
./pyapix/client/protein.py
./pyapix/client/worms.py
./pyapix/examples/__init__.py
./pyapix/examples/altair_new.py
./pyapix/examples/api_libre.py
./pyapix/examples/counties.html
./pyapix/examples/county_codes.py
./pyapix/examples/repl_libre.py
./pyapix/examples/vis/altair_good.py
./pyapix/examples/vis/altair_good.py.20250128153340
./pyapix/examples/vis/altair_good.py.20250128161328
./pyapix/examples/vis/altair_new.py
./pyapix/examples/vis/counties.html
./pyapix/examples/vis/county_codes.py
./pyapix/examples/vis/county_codes.py.20250128153323
./pyapix/examples/vis/example.svg
./pyapix/osdu/do_postman_nws.py
./pyapix/osdu/do_postman_osdu.py
./pyapix/osdu/working_with_postman.py
./pyapix/osdu/client/crs_catalog.py
./pyapix/osdu/client/crs_conversion.py
./pyapix/osdu/client/entitlements.py
./pyapix/osdu/client/legal.py
./pyapix/osdu/client/unit.py
./pyapix/test/surprise_git
./pyapix/test/test_api_tools.py
pyapix-2025.2.21.dist-info/METADATA
pyapix-2025.2.21.dist-info/WHEEL
pyapix-2025.2.21.dist-info/licenses/LICENSE
pyapix-2025.2.21.dist-info/RECORD
