Metadata-Version: 2.4
Name: pyapiX
Version: 2025.2.21
Summary: Easy API client generator
License-Expression: MIT
License-File: LICENSE
Keywords: API,OSDU,OpenAPI,REST,functional,swagger
Classifier: Development Status :: 3 - Alpha
Classifier: Intended Audience :: Developers
Classifier: Operating System :: OS Independent
Classifier: Programming Language :: Python :: 3.11
Requires-Python: >=3.11
Requires-Dist: anyio==4.6.2.post1
Requires-Dist: attrs==24.2.0
Requires-Dist: certifi==2024.8.30
Requires-Dist: exceptiongroup==1.2.2
Requires-Dist: h11==0.14.0
Requires-Dist: httpcore==1.0.6
Requires-Dist: httpx
Requires-Dist: httpx==0.27.2
Requires-Dist: idna==3.10
Requires-Dist: iniconfig==2.0.0
Requires-Dist: jinja2
Requires-Dist: jsonref==1.1.0
Requires-Dist: jsonschema-specifications==2024.10.1
Requires-Dist: jsonschema==4.23.0
Requires-Dist: numpy==2.0.2
Requires-Dist: packaging==24.1
Requires-Dist: pandas==2.2.3
Requires-Dist: pluggy==1.5.0
Requires-Dist: pytest==8.3.3
Requires-Dist: python-dateutil==2.9.0.post0
Requires-Dist: pytz==2024.2
Requires-Dist: pyyaml==6.0.2
Requires-Dist: referencing==0.35.1
Requires-Dist: rpds-py==0.20.0
Requires-Dist: six==1.16.0
Requires-Dist: sniffio==1.3.1
Requires-Dist: tomli==2.0.2
Requires-Dist: typing-extensions==4.12.2
Requires-Dist: tzdata==2024.2
